{
  "window" : {
    "background" : ":/img/oled_shield.jpg",
    "windowsize" : [470, 750]
  },
  "devices" :
  [
   { 
      "class" : "button",
      "id" : "button_b",
      "graphics" : 
      { 
        "offs" : [86, 630],
        "scale" : 2
      },
      "keybindings" : [ "B", "X", "Y", "Z"],
      "pins" :
      [
        {
          "device_pin" : 1,
          "global_pin" : 15,
          "port": "E",
          "name" : "output",
          "synchronous" : false 
        } 
      ]
    },
   { 
      "class" : "button",
      "id" : "button_a",
      "graphics" : 
      { 
        "offs" : [86, 548],
        "scale" : 2
      },
      "keybindings" : [ "A" ],
      "pins" :
      [
        {
          "device_pin" : 1,
          "global_pin" : 14,
          "port": "E",
          "name" : "output",
          "synchronous" : false 
        } 
      ]
    },
   { 
      "class" : "button",
      "id" : "button_right",
      "graphics" : 
      { 
        "offs" : [297, 592],
        "scale" : 2
      },
      "keybindings" : [ "Right" ],
      "pins" :
      [
        {
          "device_pin" : 1,
          "global_pin" : 11,
          "port": "E",
          "name" : "output",
          "synchronous" : false 
        } 
      ]
    },
   { 
      "class" : "button",
      "id" : "button_left",
      "graphics" : 
      { 
        "offs" : [155, 591],
        "scale" : 2
      },
      "keybindings" : [ "Left" ],
      "pins" :
      [
        {
          "device_pin" : 1,
          "global_pin" : 12,
          "port": "E",
          "name" : "output",
          "synchronous" : false 
        } 
      ]
    },
    { 
      "class" : "button",
      "id" : "button_up",
      "graphics" : 
      { 
        "offs" : [226, 520],
        "scale" : 2
      },
      "keybindings" : [ "Up" ],
      "pins" :
      [
        {
          "device_pin" : 1,
          "global_pin" : 13,
          "port": "E",
          "name" : "output",
          "synchronous" : false 
        } 
      ]
    },
    { 
      "class" : "button",
      "id" : "button_down",
      "graphics" : 
      { 
        "offs" : [226, 659],
        "scale" : 2
      },
      "keybindings" : [ "Down" ],
      "pins" :
      [
        {
          "device_pin" : 1,
          "global_pin" : 9,
          "port": "E",
          "name" : "output",
          "synchronous" : false 
        } 
      ]
    },
    { 
      "class" : "button",
      "id" : "button_center",
      "graphics" : 
      { 
        "offs" : [226, 590],
        "scale" : 2
      },
      "keybindings" : [ "C" ],
      "pins" :
      [
        {
          "device_pin" : 1,
          "global_pin" : 10,
          "port": "E",
          "name" : "output",
          "synchronous" : false 
        } 
      ]
    },
    {
      "class" : "oled",
      "id"    : "display",
      "spi"   :
      { 
        "cs_pin" : 4,
        "port": "A",
        "noresponse": true
      },
      "pins"  :
      [
        {
          "device_pin" : 1,
          "global_pin" : 2,
          "port": "A",
          "name": "dc_pin",
          "synchronous" : true
        }
      ],
     "graphics" :
     {
       "offs" : [105, 308],
       "scale" : 2
     }
    }
  ]
}
